setup.py
GeoMergerDI/MunMergerAlgorithm.py
GeoMergerDI/__init__.py
GeoMergerDI.egg-info/PKG-INFO
GeoMergerDI.egg-info/SOURCES.txt
GeoMergerDI.egg-info/dependency_links.txt
GeoMergerDI.egg-info/requires.txt
GeoMergerDI.egg-info/top_level.txt